siphoai/__init__.py
siphoai/__main__.py
siphoai/app.py
siphoai/cli.py
siphoai/path_manager.py
siphoai/data/commands.json
siphoai/static/icon.svg
siphoai/templates/index.html
siphoai/utils/__init__.py
siphoai/utils/command_manager.py
siphoai/utils/system_checker.py
siphoai-1.0.4.dist-info/licenses/LICENSE
siphoai-1.0.4.dist-info/METADATA
siphoai-1.0.4.dist-info/WHEEL
siphoai-1.0.4.dist-info/entry_points.txt
siphoai-1.0.4.dist-info/top_level.txt
siphoai-1.0.4.dist-info/RECORD
