Metadata-Version: 2.4
Name: siphoai
Version: 1.0.4
Summary: AI-powered voice command assistant for desktop automation
Home-page: https://github.com/niquewrld/siphoai
Author: NiqueWrld
Author-email: NiqueWrld <niquewrld@outlook.com>
License: MIT License
Project-URL: Homepage, https://github.com/NiqueWrld/siphoai
Project-URL: Bug Reports, https://github.com/NiqueWrld/siphoai/issues
Project-URL: Source, https://github.com/NiqueWrld/siphoai
Project-URL: Documentation, https://github.com/NiqueWrld/siphoai#readme
Keywords: voice assistant,desktop automation,ai assistant,voice commands,home automation,productivity,flask api,openai
Classifier: Development Status :: 4 - Beta
Classifier: Intended Audience :: End Users/Desktop
Classifier: Topic :: Desktop Environment
Classifier: Topic :: Home Automation
Classifier: Topic :: System :: Systems Administration
Classifier: License :: OSI Approved :: MIT License
Classifier: Programming Language :: Python :: 3
Classifier: Programming Language :: Python :: 3.7
Classifier: Programming Language :: Python :: 3.8
Classifier: Programming Language :: Python :: 3.9
Classifier: Programming Language :: Python :: 3.10
Classifier: Programming Language :: Python :: 3.11
Classifier: Operating System :: Microsoft :: Windows
Classifier: Operating System :: POSIX :: Linux
Classifier: Operating System :: MacOS
Requires-Python: >=3.7
License-File: LICENSE
Requires-Dist: flask>=2.3.3
Requires-Dist: flask-cors>=4.0.0
Requires-Dist: python-dotenv
Requires-Dist: openai
Requires-Dist: pillow
Requires-Dist: requests
Requires-Dist: qrcode[pil]
Requires-Dist: importlib-resources>=5.0.0; python_version < "3.9"
Provides-Extra: dev
Requires-Dist: pytest>=6.0; extra == "dev"
Requires-Dist: pytest-cov; extra == "dev"
Requires-Dist: black; extra == "dev"
Requires-Dist: flake8; extra == "dev"
Requires-Dist: mypy; extra == "dev"
Provides-Extra: voice
Requires-Dist: SpeechRecognition; extra == "voice"
Requires-Dist: pyttsx3; extra == "voice"
Requires-Dist: pyaudio; extra == "voice"
Dynamic: author
Dynamic: home-page
Dynamic: license-file
Dynamic: requires-python
